sp_ask_report_chats_per_school/__init__.py
sp_ask_report_chats_per_school-0.1.4.dist-info/WHEEL
sp_ask_report_chats_per_school-0.1.4.dist-info/METADATA
sp_ask_report_chats_per_school-0.1.4.dist-info/RECORD
