Metadata-Version: 2.1
Name: sp-ask-report-chats-per-school
Version: 0.1.4
Summary: 
Home-page: https://github.com/guinslym/sp_ask_report_chats_per_school
License: MIT
Keywords: Ask,Scholars Portal,Ontario,Chats
Author: Guinsly Mondesir
Author-email: guinslym@gmail.com
Requires-Python: >=3.7,<4.0
Classifier: License :: OSI Approved :: MIT License
Classifier: Operating System :: OS Independent
Classifier: Programming Language :: Python :: 3
Classifier: Programming Language :: Python :: 3.7
Classifier: Programming Language :: Python :: 3.8
Classifier: Topic :: Software Development :: Documentation
Classifier: Topic :: Software Development :: Libraries :: Python Modules
Classifier: Topic :: Software Development :: Quality Assurance
Requires-Dist: lh3api (>=0.2.0,<0.3.0)
Project-URL: Repository, https://github.com/guinslym/sp_ask_report_chats_per_school
